{"chunk_definitions":[{"row":17,"row_count":1,"visible":true,"expansion_state":0,"options":{"engine":"r","include":false,"label":"unnamed-chunk-2"},"document_id":"C9BEBD63","chunk_id":"crntq24bmaztj","chunk_label":"unnamed-chunk-1"},{"row":36,"row_count":1,"visible":true,"expansion_state":0,"options":{"engine":"r","label":"library"},"document_id":"51334A46","chunk_id":"c615c40xwn4tl","chunk_label":"library"},{"row":42,"row_count":1,"visible":true,"expansion_state":0,"options":{"engine":"r","label":"unnamed-chunk-3"},"document_id":"51334A46","chunk_id":"c560alwtxvz4g","chunk_label":"unnamed-chunk-2"},{"row":265,"row_count":1,"visible":true,"expansion_state":0,"options":{"engine":"r","label":"unnamed-chunk-1"},"document_id":"C9BEBD63","chunk_id":"cdtw4di6wen54","chunk_label":"unnamed-chunk-15"}],"doc_write_time":1679969870}